xlsxhelper.py
xlsxhelper-0.3.4.dist-info/licenses/LICENSE
xlsxhelper-0.3.4.dist-info/METADATA
xlsxhelper-0.3.4.dist-info/WHEEL
xlsxhelper-0.3.4.dist-info/top_level.txt
xlsxhelper-0.3.4.dist-info/RECORD
