Metadata-Version: 2.4
Name: xlsxhelper
Version: 0.3.4
Summary: Excel file manipulation toolset.
Author: rRR0VrFP
Maintainer: rRR0VrFP
License: MIT
Keywords: excel utils
Classifier: Development Status :: 5 - Production/Stable
Classifier: Intended Audience :: Developers
Classifier: Topic :: Software Development :: Libraries :: Python Modules
Classifier: License :: OSI Approved :: MIT License
Classifier: Programming Language :: Python :: 3
Classifier: Programming Language :: Python :: 3 :: Only
Requires-Python: >=2.7, !=3.2.*, !=3.3.*
License-File: LICENSE
Requires-Dist: openpyxl
Requires-Dist: zenutils
Dynamic: author
Dynamic: classifier
Dynamic: description
Dynamic: description-content-type
Dynamic: keywords
Dynamic: license
Dynamic: license-file
Dynamic: maintainer
Dynamic: requires-dist
Dynamic: requires-python
Dynamic: summary
